Metadata-Version: 2.1
Name: may-py2023
Version: 0.3
Summary: Удобный класс для работы с файлами
Author-email: gleb-grebenek1@mail.ru
